simpleasyncfilestorage/__init__.py
simpleasyncfilestorage/deta_storage.py
simpleasyncfilestorage/errors.py
simpleasyncfilestorage/local_storage.py
simpleasyncfilestorage-0.1.1.dist-info/WHEEL
simpleasyncfilestorage-0.1.1.dist-info/METADATA
simpleasyncfilestorage-0.1.1.dist-info/RECORD
